{
  "generatedAt": "2026-05-23T15:26:14.251Z",
  "domainId": "support.town_npc_maintenance",
  "panelId": "sourceReadiness",
  "status": "blocked",
  "reportPath": "reports/domain/support.town_npc_maintenance/source-readiness-2026-05-23.json",
  "requiresDatabase": false,
  "writesDatabase": false,
  "summary": {
    "checkCount": 2,
    "requiredEvidenceCount": 1,
    "optionalEvidenceCount": 1,
    "presentEvidenceCount": 0,
    "missingEvidenceCount": 2,
    "blockedCount": 1,
    "warningCount": 1
  },
  "blockingReasons": [
    "Missing required evidence: data/generated/wiki-town-npc-maintenance.latest.json"
  ],
  "warningReasons": [
    "Missing optional evidence: reports/wiki-town-npc-import*.json"
  ],
  "checks": [
    {
      "id": "data_generated_wiki_town_npc_maintenance_latest_json",
      "type": "json",
      "required": true,
      "found": false,
      "readable": false,
      "evidencePath": "data/generated/wiki-town-npc-maintenance.latest.json",
      "latestReportPath": null,
      "recordCount": null,
      "status": "blocked",
      "message": "Missing required evidence: data/generated/wiki-town-npc-maintenance.latest.json"
    },
    {
      "id": "reports_wiki_town_npc_importlatest_json",
      "type": "json",
      "required": false,
      "found": false,
      "readable": false,
      "evidencePath": "reports/wiki-town-npc-import*.json",
      "latestReportPath": null,
      "recordCount": null,
      "status": "warning",
      "message": "Missing optional evidence: reports/wiki-town-npc-import*.json"
    }
  ]
}
