[
  {
    "entityType": "item",
    "fetchedAt": "2026-03-28T04:21:58.709Z",
    "hasHtml": true,
    "hasRecipesMarkup": true,
    "hasWikitext": true,
    "htmlLength": 1708,
    "itemInternalName": "WilsonShirt",
    "itemName": "Gentleman's Vest",
    "pageId": 8755,
    "pageTitle": "Gentleman's Vest",
    "recipesMarkupLength": 0,
    "requestedPageTitle": "Gentleman's Vest",
    "revisionTimestamp": "2025-07-23T06:46:16Z",
    "sourceApi": "https://terraria.wiki.gg/api.php",
    "sourceFile": "terraPedia/data/raw/wiki/item-pages/wilsonshirt.latest.json",
    "wikitextLength": 108
  },
  {
    "entityType": "item",
    "fetchedAt": "2026-03-28T04:43:50.680Z",
    "hasHtml": true,
    "hasRecipesMarkup": true,
    "hasWikitext": true,
    "htmlLength": 129897,
    "itemInternalName": "WiltedClover",
    "itemName": "Wilted Clover",
    "pageId": 71078,
    "pageTitle": "Wilted Clover",
    "recipesMarkupLength": 0,
    "requestedPageTitle": "Wilted Clover",
    "revisionTimestamp": "2026-03-14T12:42:45Z",
    "sourceApi": "https://terraria.wiki.gg/api.php",
    "sourceFile": "terraPedia/data/raw/wiki/item-pages/wiltedclover.latest.json",
    "wikitextLength": 1031
  },
  {
    "entityType": "item",
    "fetchedAt": "2026-03-28T02:35:34.620Z",
    "hasHtml": true,
    "hasRecipesMarkup": true,
    "hasWikitext": true,
    "htmlLength": 1667,
    "itemInternalName": "WineGlass",
    "itemName": "Wine Glass",
    "pageId": 9810,
    "pageTitle": "Wine Glass",
    "recipesMarkupLength": 0,
    "requestedPageTitle": "Wine Glass",
    "revisionTimestamp": "2025-07-23T18:10:23Z",
    "sourceApi": "https://terraria.wiki.gg/api.php",
    "sourceFile": "terraPedia/data/raw/wiki/item-pages/wineglass.latest.json",
    "wikitextLength": 180
  },
  {
    "entityType": "item",
    "fetchedAt": "2026-03-28T03:20:18.628Z",
    "hasHtml": true,
    "hasRecipesMarkup": true,
    "hasWikitext": true,
    "htmlLength": 1699,
    "itemInternalName": "WingsNebula",
    "itemName": "Nebula Mantle",
    "pageId": 12682,
    "pageTitle": "Nebula Mantle",
    "recipesMarkupLength": 0,
    "requestedPageTitle": "Nebula Mantle",
    "revisionTimestamp": "2025-07-24T09:38:10Z",
    "sourceApi": "https://terraria.wiki.gg/api.php",
    "sourceFile": "terraPedia/data/raw/wiki/item-pages/wingsnebula.latest.json",
    "wikitextLength": 251
  },
  {
    "entityType": "item",
    "fetchedAt": "2026-03-28T04:27:02.939Z",
    "hasHtml": true,
    "hasRecipesMarkup": true,
    "hasWikitext": true,
    "htmlLength": 1710,
    "itemInternalName": "WingsofEvil",
    "itemName": "Wings of Evil",
    "pageId": 59550,
    "pageTitle": "Wings of Evil",
    "recipesMarkupLength": 0,
    "requestedPageTitle": "Wings of Evil",
    "revisionTimestamp": "2025-07-24T10:44:50Z",
    "sourceApi": "https://terraria.wiki.gg/api.php",
    "sourceFile": "terraPedia/data/raw/wiki/item-pages/wingsofevil.latest.json",
    "wikitextLength": 98
  },
  {
    "entityType": "item",
    "fetchedAt": "2026-03-28T03:20:15.261Z",
    "hasHtml": true,
    "hasRecipesMarkup": true,
    "hasWikitext": true,
    "htmlLength": 1695,
    "itemInternalName": "WingsSolar",
    "itemName": "Solar Wings",
    "pageId": 12549,
    "pageTitle": "Solar Wings",
    "recipesMarkupLength": 0,
    "requestedPageTitle": "Solar Wings",
    "revisionTimestamp": "2025-07-24T10:16:53Z",
    "sourceApi": "https://terraria.wiki.gg/api.php",
    "sourceFile": "terraPedia/data/raw/wiki/item-pages/wingssolar.latest.json",
    "wikitextLength": 248
  },
  {
    "entityType": "item",
    "fetchedAt": "2026-03-28T03:20:20.404Z",
    "hasHtml": true,
    "hasRecipesMarkup": true,
    "hasWikitext": true,
    "htmlLength": 1701,
    "itemInternalName": "WingsStardust",
    "itemName": "Stardust Wings",
    "pageId": 10425,
    "pageTitle": "Stardust Wings",
    "recipesMarkupLength": 0,
    "requestedPageTitle": "Stardust Wings",
    "revisionTimestamp": "2025-07-24T10:23:41Z",
    "sourceApi": "https://terraria.wiki.gg/api.php",
    "sourceFile": "terraPedia/data/raw/wiki/item-pages/wingsstardust.latest.json",
    "wikitextLength": 251
  },
  {
    "entityType": "item",
    "fetchedAt": "2026-03-28T03:20:17.034Z",
    "hasHtml": true,
    "hasRecipesMarkup": true,
    "hasWikitext": true,
    "htmlLength": 1700,
    "itemInternalName": "WingsVortex",
    "itemName": "Vortex Booster",
    "pageId": 6793,
    "pageTitle": "Vortex Booster",
    "recipesMarkupLength": 0,
    "requestedPageTitle": "Vortex Booster",
    "revisionTimestamp": "2025-07-24T10:41:01Z",
    "sourceApi": "https://terraria.wiki.gg/api.php",
    "sourceFile": "terraPedia/data/raw/wiki/item-pages/wingsvortex.latest.json",
    "wikitextLength": 251
  },
  {
    "entityType": "item",
    "fetchedAt": "2026-03-28T04:39:47.775Z",
    "hasHtml": true,
    "hasRecipesMarkup": true,
    "hasWikitext": true,
    "htmlLength": 1730,
    "itemInternalName": "WinterAtVaringskollen",
    "itemName": "Winter At Varingskollen",
    "pageId": 71771,
    "pageTitle": "Winter At Varingskollen",
    "recipesMarkupLength": 0,
    "requestedPageTitle": "Winter At Varingskollen",
    "revisionTimestamp": "2026-02-03T00:11:09Z",
    "sourceApi": "https://terraria.wiki.gg/api.php",
    "sourceFile": "terraPedia/data/raw/wiki/item-pages/winteratvaringskollen.latest.json",
    "wikitextLength": 110
  },
  {
    "entityType": "item",
    "fetchedAt": "2026-03-28T02:37:08.946Z",
    "hasHtml": true,
    "hasRecipesMarkup": true,
    "hasWikitext": true,
    "htmlLength": 1670,
    "itemInternalName": "WinterCape",
    "itemName": "Winter Cape",
    "pageId": 10838,
    "pageTitle": "Winter Cape",
    "recipesMarkupLength": 0,
    "requestedPageTitle": "Winter Cape",
    "revisionTimestamp": "2025-07-24T22:59:46Z",
    "sourceApi": "https://terraria.wiki.gg/api.php",
    "sourceFile": "terraPedia/data/raw/wiki/item-pages/wintercape.latest.json",
    "wikitextLength": 243
  },
  {
    "entityType": "item",
    "fetchedAt": "2026-03-28T01:40:21.956Z",
    "hasHtml": true,
    "hasRecipesMarkup": true,
    "hasWikitext": true,
    "htmlLength": 333983,
    "itemInternalName": "Wire",
    "itemName": "Wire",
    "pageId": 6681,
    "pageTitle": "Wire",
    "recipesMarkupLength": 0,
    "requestedPageTitle": "Wire",
    "revisionTimestamp": "2026-03-26T18:29:41Z",
    "sourceApi": "https://terraria.wiki.gg/api.php",
    "sourceFile": "terraPedia/data/raw/wiki/item-pages/wire.latest.json",
    "wikitextLength": 5385
  },
  {
    "entityType": "item",
    "fetchedAt": "2026-03-28T03:27:43.624Z",
    "hasHtml": true,
    "hasRecipesMarkup": true,
    "hasWikitext": true,
    "htmlLength": 84322,
    "itemInternalName": "WireBulb",
    "itemName": "Wire Bulb",
    "pageId": 6511,
    "pageTitle": "Wire Bulb",
    "recipesMarkupLength": 0,
    "requestedPageTitle": "Wire Bulb",
    "revisionTimestamp": "2025-02-11T04:53:02Z",
    "sourceApi": "https://terraria.wiki.gg/api.php",
    "sourceFile": "terraPedia/data/raw/wiki/item-pages/wirebulb.latest.json",
    "wikitextLength": 1029
  },
  {
    "entityType": "item",
    "fetchedAt": "2026-03-28T01:39:39.196Z",
    "hasHtml": true,
    "hasRecipesMarkup": true,
    "hasWikitext": true,
    "htmlLength": 128209,
    "itemInternalName": "WireCutter",
    "itemName": "Wire Cutter",
    "pageId": 14243,
    "pageTitle": "Wire Cutter",
    "recipesMarkupLength": 0,
    "requestedPageTitle": "Wire Cutter",
    "revisionTimestamp": "2025-08-25T14:29:23Z",
    "sourceApi": "https://terraria.wiki.gg/api.php",
    "sourceFile": "terraPedia/data/raw/wiki/item-pages/wirecutter.latest.json",
    "wikitextLength": 1773
  },
  {
    "entityType": "item",
    "fetchedAt": "2026-03-28T03:26:57.158Z",
    "hasHtml": true,
    "hasRecipesMarkup": true,
    "hasWikitext": true,
    "htmlLength": 157593,
    "itemInternalName": "WireKite",
    "itemName": "The Grand Design",
    "pageId": 6950,
    "pageTitle": "The Grand Design",
    "recipesMarkupLength": 1821,
    "requestedPageTitle": "The Grand Design",
    "revisionTimestamp": "2025-11-24T02:37:12Z",
    "sourceApi": "https://terraria.wiki.gg/api.php",
    "sourceFile": "terraPedia/data/raw/wiki/item-pages/wirekite.latest.json",
    "wikitextLength": 6431
  },
  {
    "entityType": "item",
    "fetchedAt": "2026-03-28T03:27:08.214Z",
    "hasHtml": true,
    "hasRecipesMarkup": true,
    "hasWikitext": true,
    "htmlLength": 84245,
    "itemInternalName": "WirePipe",
    "itemName": "Junction Box",
    "pageId": 6660,
    "pageTitle": "Junction Box",
    "recipesMarkupLength": 0,
    "requestedPageTitle": "Junction Box",
    "revisionTimestamp": "2025-02-11T03:51:29Z",
    "sourceApi": "https://terraria.wiki.gg/api.php",
    "sourceFile": "terraPedia/data/raw/wiki/item-pages/wirepipe.latest.json",
    "wikitextLength": 1056
  },
  {
    "entityType": "item",
    "fetchedAt": "2026-03-28T02:58:41.397Z",
    "hasHtml": true,
    "hasRecipesMarkup": true,
    "hasWikitext": true,
    "htmlLength": 170413,
    "itemInternalName": "WispDye",
    "itemName": "Wisp Dye",
    "pageId": 15620,
    "pageTitle": "Wisp Dye",
    "recipesMarkupLength": 0,
    "requestedPageTitle": "Wisp Dye",
    "revisionTimestamp": "2025-02-11T03:07:50Z",
    "sourceApi": "https://terraria.wiki.gg/api.php",
    "sourceFile": "terraPedia/data/raw/wiki/item-pages/wispdye.latest.json",
    "wikitextLength": 845
  },
  {
    "entityType": "item",
    "fetchedAt": "2026-03-28T02:02:30.093Z",
    "hasHtml": true,
    "hasRecipesMarkup": true,
    "hasWikitext": true,
    "htmlLength": 255895,
    "itemInternalName": "WispinaBottle",
    "itemName": "Wisp in a Bottle",
    "pageId": 10877,
    "pageTitle": "Wisp in a Bottle",
    "recipesMarkupLength": 0,
    "requestedPageTitle": "Wisp in a Bottle",
    "revisionTimestamp": "2025-10-28T02:55:28Z",
    "sourceApi": "https://terraria.wiki.gg/api.php",
    "sourceFile": "terraPedia/data/raw/wiki/item-pages/wispinabottle.latest.json",
    "wikitextLength": 3616
  },
  {
    "entityType": "item",
    "fetchedAt": "2026-03-28T02:21:05.091Z",
    "hasHtml": true,
    "hasRecipesMarkup": true,
    "hasWikitext": true,
    "htmlLength": 1364,
    "itemInternalName": "WitchBoots",
    "itemName": "Witch Boots",
    "pageId": 6493,
    "pageTitle": "Witch Boots",
    "recipesMarkupLength": 0,
    "requestedPageTitle": "Witch Boots",
    "revisionTimestamp": "2025-07-23T17:22:20Z",
    "sourceApi": "https://terraria.wiki.gg/api.php",
    "sourceFile": "terraPedia/data/raw/wiki/item-pages/witchboots.latest.json",
    "wikitextLength": 147
  },
  {
    "entityType": "item",
    "fetchedAt": "2026-03-28T03:57:04.425Z",
    "hasHtml": true,
    "hasRecipesMarkup": true,
    "hasWikitext": true,
    "htmlLength": 271902,
    "itemInternalName": "WitchBroom",
    "itemName": "Witch's Broom",
    "pageId": 15538,
    "pageTitle": "Witch's Broom",
    "recipesMarkupLength": 0,
    "requestedPageTitle": "Witch's Broom",
    "revisionTimestamp": "2026-02-08T08:10:07Z",
    "sourceApi": "https://terraria.wiki.gg/api.php",
    "sourceFile": "terraPedia/data/raw/wiki/item-pages/witchbroom.latest.json",
    "wikitextLength": 3998
  },
  {
    "entityType": "item",
    "fetchedAt": "2026-03-28T02:21:03.661Z",
    "hasHtml": true,
    "hasRecipesMarkup": true,
    "hasWikitext": true,
    "htmlLength": 1365,
    "itemInternalName": "WitchDress",
    "itemName": "Witch Dress",
    "pageId": 11168,
    "pageTitle": "Witch Dress",
    "recipesMarkupLength": 0,
    "requestedPageTitle": "Witch Dress",
    "revisionTimestamp": "2025-07-23T17:22:09Z",
    "sourceApi": "https://terraria.wiki.gg/api.php",
    "sourceFile": "terraPedia/data/raw/wiki/item-pages/witchdress.latest.json",
    "wikitextLength": 147
  },
  {
    "entityType": "item",
    "fetchedAt": "2026-03-28T02:20:48.602Z",
    "hasHtml": true,
    "hasRecipesMarkup": true,
    "hasWikitext": true,
    "htmlLength": 1359,
    "itemInternalName": "WitchHat",
    "itemName": "Witch Hat",
    "pageId": 11509,
    "pageTitle": "Witch Hat",
    "recipesMarkupLength": 0,
    "requestedPageTitle": "Witch Hat",
    "revisionTimestamp": "2025-07-23T17:22:00Z",
    "sourceApi": "https://terraria.wiki.gg/api.php",
    "sourceFile": "terraPedia/data/raw/wiki/item-pages/witchhat.latest.json",
    "wikitextLength": 147
  },
  {
    "entityType": "item",
    "fetchedAt": "2026-03-28T01:32:04.373Z",
    "hasHtml": true,
    "hasRecipesMarkup": true,
    "hasWikitext": true,
    "htmlLength": 175720,
    "itemInternalName": "WizardHat",
    "itemName": "Wizard Hat",
    "pageId": 14632,
    "pageTitle": "Wizard Hat",
    "recipesMarkupLength": 0,
    "requestedPageTitle": "Wizard Hat",
    "revisionTimestamp": "2026-02-12T06:57:58Z",
    "sourceApi": "https://terraria.wiki.gg/api.php",
    "sourceFile": "terraPedia/data/raw/wiki/item-pages/wizardhat.latest.json",
    "wikitextLength": 2139
  },
  {
    "entityType": "item",
    "fetchedAt": "2026-03-28T02:20:05.989Z",
    "hasHtml": true,
    "hasRecipesMarkup": true,
    "hasWikitext": true,
    "htmlLength": 170111,
    "itemInternalName": "WizardsHat",
    "itemName": "Wizard's Hat",
    "pageId": 11447,
    "pageTitle": "Wizard's Hat",
    "recipesMarkupLength": 0,
    "requestedPageTitle": "Wizard's Hat",
    "revisionTimestamp": "2025-06-09T17:13:05Z",
    "sourceApi": "https://terraria.wiki.gg/api.php",
    "sourceFile": "terraPedia/data/raw/wiki/item-pages/wizardshat.latest.json",
    "wikitextLength": 976
  },
  {
    "entityType": "item",
    "fetchedAt": "2026-03-28T02:18:44.041Z",
    "hasHtml": true,
    "hasRecipesMarkup": true,
    "hasWikitext": true,
    "htmlLength": 1400,
    "itemInternalName": "WolfBanner",
    "itemName": "Wolf Banner",
    "pageId": 4470,
    "pageTitle": "Wolf Banner",
    "recipesMarkupLength": 0,
    "requestedPageTitle": "Wolf Banner",
    "revisionTimestamp": "2025-07-24T10:44:58Z",
    "sourceApi": "https://terraria.wiki.gg/api.php",
    "sourceFile": "terraPedia/data/raw/wiki/item-pages/wolfbanner.latest.json",
    "wikitextLength": 195
  },
  {
    "entityType": "item",
    "fetchedAt": "2026-03-28T02:23:11.785Z",
    "hasHtml": true,
    "hasRecipesMarkup": true,
    "hasWikitext": true,
    "htmlLength": 1362,
    "itemInternalName": "WolfMask",
    "itemName": "Wolf Mask",
    "pageId": 12392,
    "pageTitle": "Wolf Mask",
    "recipesMarkupLength": 0,
    "requestedPageTitle": "Wolf Mask",
    "revisionTimestamp": "2025-07-23T17:22:53Z",
    "sourceApi": "https://terraria.wiki.gg/api.php",
    "sourceFile": "terraPedia/data/raw/wiki/item-pages/wolfmask.latest.json",
    "wikitextLength": 146
  },
  {
    "entityType": "item",
    "fetchedAt": "2026-03-28T04:23:16.526Z",
    "hasHtml": true,
    "hasRecipesMarkup": true,
    "hasWikitext": true,
    "htmlLength": 255058,
    "itemInternalName": "WolfMountItem",
    "itemName": "Lilith's Necklace",
    "pageId": 59432,
    "pageTitle": "Lilith's Necklace",
    "recipesMarkupLength": 0,
    "requestedPageTitle": "Lilith's Necklace",
    "revisionTimestamp": "2026-02-25T07:57:34Z",
    "sourceApi": "https://terraria.wiki.gg/api.php",
    "sourceFile": "terraPedia/data/raw/wiki/item-pages/wolfmountitem.latest.json",
    "wikitextLength": 3227
  },
  {
    "entityType": "item",
    "fetchedAt": "2026-03-28T02:23:14.597Z",
    "hasHtml": true,
    "hasRecipesMarkup": true,
    "hasWikitext": true,
    "htmlLength": 1361,
    "itemInternalName": "WolfPants",
    "itemName": "Wolf Pants",
    "pageId": 6092,
    "pageTitle": "Wolf Pants",
    "recipesMarkupLength": 0,
    "requestedPageTitle": "Wolf Pants",
    "revisionTimestamp": "2025-07-23T17:23:13Z",
    "sourceApi": "https://terraria.wiki.gg/api.php",
    "sourceFile": "terraPedia/data/raw/wiki/item-pages/wolfpants.latest.json",
    "wikitextLength": 146
  },
  {
    "entityType": "item",
    "fetchedAt": "2026-03-28T02:23:13.076Z",
    "hasHtml": true,
    "hasRecipesMarkup": true,
    "hasWikitext": true,
    "htmlLength": 1361,
    "itemInternalName": "WolfShirt",
    "itemName": "Wolf Shirt",
    "pageId": 7059,
    "pageTitle": "Wolf Shirt",
    "recipesMarkupLength": 0,
    "requestedPageTitle": "Wolf Shirt",
    "revisionTimestamp": "2025-07-23T17:23:01Z",
    "sourceApi": "https://terraria.wiki.gg/api.php",
    "sourceFile": "terraPedia/data/raw/wiki/item-pages/wolfshirt.latest.json",
    "wikitextLength": 146
  },
  {
    "entityType": "item",
    "fetchedAt": "2026-03-28T02:28:10.912Z",
    "hasHtml": true,
    "hasRecipesMarkup": true,
    "hasWikitext": true,
    "htmlLength": 100417,
    "itemInternalName": "Womannquin",
    "itemName": "Womannequin",
    "pageId": 12743,
    "pageTitle": "Womannequin",
    "recipesMarkupLength": 922,
    "requestedPageTitle": "Womannequin",
    "revisionTimestamp": "2026-03-25T00:25:18Z",
    "sourceApi": "https://terraria.wiki.gg/api.php",
    "sourceFile": "terraPedia/data/raw/wiki/item-pages/womannquin.latest.json",
    "wikitextLength": 2413
  },
  {
    "entityType": "item",
    "fetchedAt": "2026-03-28T01:37:35.432Z",
    "hasHtml": true,
    "hasRecipesMarkup": true,
    "hasWikitext": true,
    "htmlLength": 1503,
    "itemInternalName": "WomanStatue",
    "itemName": "Woman Statue",
    "pageId": 4218,
    "pageTitle": "Woman Statue",
    "recipesMarkupLength": 0,
    "requestedPageTitle": "Woman Statue",
    "revisionTimestamp": "2025-07-24T10:45:03Z",
    "sourceApi": "https://terraria.wiki.gg/api.php",
    "sourceFile": "terraPedia/data/raw/wiki/item-pages/womanstatue.latest.json",
    "wikitextLength": 514
  },
  {
    "entityType": "item",
    "fetchedAt": "2026-03-27T11:14:07.391Z",
    "hasHtml": true,
    "hasRecipesMarkup": true,
    "hasWikitext": true,
    "htmlLength": 1458,
    "itemInternalName": "Wood",
    "itemName": "Wood",
    "pageId": 8568,
    "pageTitle": "Wood",
    "recipesMarkupLength": 0,
    "requestedPageTitle": "Wood",
    "revisionTimestamp": "2025-07-23T05:04:14Z",
    "sourceApi": "https://terraria.wiki.gg/api.php",
    "sourceFile": "terraPedia/data/raw/wiki/item-pages/wood.latest.json",
    "wikitextLength": 422
  },
  {
    "entityType": "item",
    "fetchedAt": "2026-03-28T01:47:39.868Z",
    "hasHtml": true,
    "hasRecipesMarkup": true,
    "hasWikitext": true,
    "htmlLength": 1096,
    "itemInternalName": "WoodBreastplate",
    "itemName": "Wood Breastplate",
    "pageId": 5111,
    "pageTitle": "Wood Breastplate",
    "recipesMarkupLength": 0,
    "requestedPageTitle": "Wood Breastplate",
    "revisionTimestamp": "2025-07-24T10:45:07Z",
    "sourceApi": "https://terraria.wiki.gg/api.php",
    "sourceFile": "terraPedia/data/raw/wiki/item-pages/woodbreastplate.latest.json",
    "wikitextLength": 52
  },
  {
    "entityType": "item",
    "fetchedAt": "2026-03-27T11:14:22.079Z",
    "hasHtml": true,
    "hasRecipesMarkup": true,
    "hasWikitext": true,
    "htmlLength": 184263,
    "itemInternalName": "WoodenArrow",
    "itemName": "Wooden Arrow",
    "pageId": 14728,
    "pageTitle": "Wooden Arrow",
    "recipesMarkupLength": 1924,
    "requestedPageTitle": "Wooden Arrow",
    "revisionTimestamp": "2026-01-26T05:14:16Z",
    "sourceApi": "https://terraria.wiki.gg/api.php",
    "sourceFile": "terraPedia/data/raw/wiki/item-pages/woodenarrow.latest.json",
    "wikitextLength": 3207
  },
  {
    "entityType": "item",
    "fetchedAt": "2026-03-28T01:38:26.124Z",
    "hasHtml": true,
    "hasRecipesMarkup": true,
    "hasWikitext": true,
    "htmlLength": 1081,
    "itemInternalName": "WoodenBeam",
    "itemName": "Wooden Beam",
    "pageId": 3956,
    "pageTitle": "Wooden Beam",
    "recipesMarkupLength": 0,
    "requestedPageTitle": "Wooden Beam",
    "revisionTimestamp": "2025-07-24T10:45:29Z",
    "sourceApi": "https://terraria.wiki.gg/api.php",
    "sourceFile": "terraPedia/data/raw/wiki/item-pages/woodenbeam.latest.json",
    "wikitextLength": 97
  },
  {
    "entityType": "item",
    "fetchedAt": "2026-03-28T01:33:00.081Z",
    "hasHtml": true,
    "hasRecipesMarkup": true,
    "hasWikitext": true,
    "htmlLength": 129614,
    "itemInternalName": "WoodenBoomerang",
    "itemName": "Wooden Boomerang",
    "pageId": 14185,
    "pageTitle": "Wooden Boomerang",
    "recipesMarkupLength": 0,
    "requestedPageTitle": "Wooden Boomerang",
    "revisionTimestamp": "2026-03-20T17:36:37Z",
    "sourceApi": "https://terraria.wiki.gg/api.php",
    "sourceFile": "terraPedia/data/raw/wiki/item-pages/woodenboomerang.latest.json",
    "wikitextLength": 3016
  },
  {
    "entityType": "item",
    "fetchedAt": "2026-03-27T11:14:21.834Z",
    "hasHtml": true,
    "hasRecipesMarkup": true,
    "hasWikitext": true,
    "htmlLength": 131819,
    "itemInternalName": "WoodenBow",
    "itemName": "Wooden Bow",
    "pageId": 13120,
    "pageTitle": "Wooden Bow",
    "recipesMarkupLength": 729,
    "requestedPageTitle": "Wooden Bow",
    "revisionTimestamp": "2025-08-25T14:29:28Z",
    "sourceApi": "https://terraria.wiki.gg/api.php",
    "sourceFile": "terraPedia/data/raw/wiki/item-pages/woodenbow.latest.json",
    "wikitextLength": 863
  },
  {
    "entityType": "item",
    "fetchedAt": "2026-03-27T11:14:20.010Z",
    "hasHtml": true,
    "hasRecipesMarkup": true,
    "hasWikitext": true,
    "htmlLength": 1350,
    "itemInternalName": "WoodenChair",
    "itemName": "Wooden Chair",
    "pageId": 15448,
    "pageTitle": "Wooden Chair",
    "recipesMarkupLength": 0,
    "requestedPageTitle": "Wooden Chair",
    "revisionTimestamp": "2025-07-24T10:45:34Z",
    "sourceApi": "https://terraria.wiki.gg/api.php",
    "sourceFile": "terraPedia/data/raw/wiki/item-pages/woodenchair.latest.json",
    "wikitextLength": 485
  },
  {
    "entityType": "item",
    "fetchedAt": "2026-03-28T02:39:12.844Z",
    "hasHtml": true,
    "hasRecipesMarkup": true,
    "hasWikitext": true,
    "htmlLength": 166279,
    "itemInternalName": "WoodenCrate",
    "itemName": "Wooden Crate",
    "pageId": 11785,
    "pageTitle": "Wooden Crate",
    "recipesMarkupLength": 0,
    "requestedPageTitle": "Wooden Crate",
    "revisionTimestamp": "2026-01-26T05:14:24Z",
    "sourceApi": "https://terraria.wiki.gg/api.php",
    "sourceFile": "terraPedia/data/raw/wiki/item-pages/woodencrate.latest.json",
    "wikitextLength": 4732
  },
  {
    "entityType": "item",
    "fetchedAt": "2026-03-28T03:39:26.099Z",
    "hasHtml": true,
    "hasRecipesMarkup": true,
    "hasWikitext": true,
    "htmlLength": 166610,
    "itemInternalName": "WoodenCrateHard",
    "itemName": "Pearlwood Crate",
    "pageId": 6316,
    "pageTitle": "Pearlwood Crate",
    "recipesMarkupLength": 0,
    "requestedPageTitle": "Pearlwood Crate",
    "revisionTimestamp": "2026-01-26T05:05:04Z",
    "sourceApi": "https://terraria.wiki.gg/api.php",
    "sourceFile": "terraPedia/data/raw/wiki/item-pages/woodencratehard.latest.json",
    "wikitextLength": 4273
  },
  {
    "entityType": "item",
    "fetchedAt": "2026-03-27T11:14:16.051Z",
    "hasHtml": true,
    "hasRecipesMarkup": true,
    "hasWikitext": true,
    "htmlLength": 1346,
    "itemInternalName": "WoodenDoor",
    "itemName": "Wooden Door",
    "pageId": 6526,
    "pageTitle": "Wooden Door",
    "recipesMarkupLength": 0,
    "requestedPageTitle": "Wooden Door",
    "revisionTimestamp": "2025-07-24T10:45:38Z",
    "sourceApi": "https://terraria.wiki.gg/api.php",
    "sourceFile": "terraPedia/data/raw/wiki/item-pages/woodendoor.latest.json",
    "wikitextLength": 385
  },
  {
    "entityType": "item",
    "fetchedAt": "2026-03-28T02:11:41.004Z",
    "hasHtml": true,
    "hasRecipesMarkup": true,
    "hasWikitext": true,
    "htmlLength": 1079,
    "itemInternalName": "WoodenFence",
    "itemName": "Wooden Fence",
    "pageId": 12983,
    "pageTitle": "Wooden Fence",
    "recipesMarkupLength": 0,
    "requestedPageTitle": "Wooden Fence",
    "revisionTimestamp": "2025-07-23T05:23:50Z",
    "sourceApi": "https://terraria.wiki.gg/api.php",
    "sourceFile": "terraPedia/data/raw/wiki/item-pages/woodenfence.latest.json",
    "wikitextLength": 49
  },
  {
    "entityType": "item",
    "fetchedAt": "2026-03-28T01:31:19.959Z",
    "hasHtml": true,
    "hasRecipesMarkup": true,
    "hasWikitext": true,
    "htmlLength": 121925,
    "itemInternalName": "WoodenHammer",
    "itemName": "Wooden Hammer",
    "pageId": 11679,
    "pageTitle": "Wooden Hammer",
    "recipesMarkupLength": 743,
    "requestedPageTitle": "Wooden Hammer",
    "revisionTimestamp": "2025-11-10T04:52:54Z",
    "sourceApi": "https://terraria.wiki.gg/api.php",
    "sourceFile": "terraPedia/data/raw/wiki/item-pages/woodenhammer.latest.json",
    "wikitextLength": 1136
  },
  {
    "entityType": "item",
    "fetchedAt": "2026-03-28T02:56:48.401Z",
    "hasHtml": true,
    "hasRecipesMarkup": true,
    "hasWikitext": true,
    "htmlLength": 1670,
    "itemInternalName": "WoodenSink",
    "itemName": "Wooden Sink",
    "pageId": 6830,
    "pageTitle": "Wooden Sink",
    "recipesMarkupLength": 0,
    "requestedPageTitle": "Wooden Sink",
    "revisionTimestamp": "2026-02-21T10:35:52Z",
    "sourceApi": "https://terraria.wiki.gg/api.php",
    "sourceFile": "terraPedia/data/raw/wiki/item-pages/woodensink.latest.json",
    "wikitextLength": 445
  },
  {
    "entityType": "item",
    "fetchedAt": "2026-03-28T02:01:24.041Z",
    "hasHtml": true,
    "hasRecipesMarkup": true,
    "hasWikitext": true,
    "htmlLength": 138812,
    "itemInternalName": "WoodenSpike",
    "itemName": "Wooden Spike",
    "pageId": 13329,
    "pageTitle": "Wooden Spike",
    "recipesMarkupLength": 0,
    "requestedPageTitle": "Wooden Spike",
    "revisionTimestamp": "2026-02-19T19:44:59Z",
    "sourceApi": "https://terraria.wiki.gg/api.php",
    "sourceFile": "terraPedia/data/raw/wiki/item-pages/woodenspike.latest.json",
    "wikitextLength": 2716
  },
  {
    "entityType": "item",
    "fetchedAt": "2026-03-27T11:14:13.432Z",
    "hasHtml": true,
    "hasRecipesMarkup": true,
    "hasWikitext": true,
    "htmlLength": 130002,
    "itemInternalName": "WoodenSword",
    "itemName": "Wooden Sword",
    "pageId": 8848,
    "pageTitle": "Wooden Sword",
    "recipesMarkupLength": 738,
    "requestedPageTitle": "Wooden Sword",
    "revisionTimestamp": "2025-09-15T23:02:10Z",
    "sourceApi": "https://terraria.wiki.gg/api.php",
    "sourceFile": "terraPedia/data/raw/wiki/item-pages/woodensword.latest.json",
    "wikitextLength": 789
  },
  {
    "entityType": "item",
    "fetchedAt": "2026-03-27T11:14:16.517Z",
    "hasHtml": true,
    "hasRecipesMarkup": true,
    "hasWikitext": true,
    "htmlLength": 1356,
    "itemInternalName": "WoodenTable",
    "itemName": "Wooden Table",
    "pageId": 15151,
    "pageTitle": "Wooden Table",
    "recipesMarkupLength": 0,
    "requestedPageTitle": "Wooden Table",
    "revisionTimestamp": "2025-07-24T10:45:43Z",
    "sourceApi": "https://terraria.wiki.gg/api.php",
    "sourceFile": "terraPedia/data/raw/wiki/item-pages/woodentable.latest.json",
    "wikitextLength": 451
  },
  {
    "entityType": "item",
    "fetchedAt": "2026-03-28T02:37:12.444Z",
    "hasHtml": true,
    "hasRecipesMarkup": true,
    "hasWikitext": true,
    "htmlLength": 1136,
    "itemInternalName": "WoodFishingPole",
    "itemName": "Wood Fishing Pole",
    "pageId": 13304,
    "pageTitle": "Wood Fishing Pole",
    "recipesMarkupLength": 0,
    "requestedPageTitle": "Wood Fishing Pole",
    "revisionTimestamp": "2025-07-24T22:59:51Z",
    "sourceApi": "https://terraria.wiki.gg/api.php",
    "sourceFile": "terraPedia/data/raw/wiki/item-pages/woodfishingpole.latest.json",
    "wikitextLength": 73
  },
  {
    "entityType": "item",
    "fetchedAt": "2026-03-28T01:47:41.129Z",
    "hasHtml": true,
    "hasRecipesMarkup": true,
    "hasWikitext": true,
    "htmlLength": 1090,
    "itemInternalName": "WoodGreaves",
    "itemName": "Wood Greaves",
    "pageId": 4444,
    "pageTitle": "Wood Greaves",
    "recipesMarkupLength": 0,
    "requestedPageTitle": "Wood Greaves",
    "revisionTimestamp": "2025-07-24T10:45:12Z",
    "sourceApi": "https://terraria.wiki.gg/api.php",
    "sourceFile": "terraPedia/data/raw/wiki/item-pages/woodgreaves.latest.json",
    "wikitextLength": 52
  },
  {
    "entityType": "item",
    "fetchedAt": "2026-03-28T01:47:38.647Z",
    "hasHtml": true,
    "hasRecipesMarkup": true,
    "hasWikitext": true,
    "htmlLength": 1097,
    "itemInternalName": "WoodHelmet",
    "itemName": "Wood Helmet",
    "pageId": 15888,
    "pageTitle": "Wood Helmet",
    "recipesMarkupLength": 0,
    "requestedPageTitle": "Wood Helmet",
    "revisionTimestamp": "2025-07-24T10:45:16Z",
    "sourceApi": "https://terraria.wiki.gg/api.php",
    "sourceFile": "terraPedia/data/raw/wiki/item-pages/woodhelmet.latest.json",
    "wikitextLength": 52
  },
  {
    "entityType": "item",
    "fetchedAt": "2026-03-28T01:06:47.268Z",
    "hasHtml": true,
    "hasRecipesMarkup": true,
    "hasWikitext": true,
    "htmlLength": 1358,
    "itemInternalName": "WoodPlatform",
    "itemName": "Wood Platform",
    "pageId": 5229,
    "pageTitle": "Wood Platform",
    "recipesMarkupLength": 0,
    "requestedPageTitle": "Wood Platform",
    "revisionTimestamp": "2025-07-24T10:45:20Z",
    "sourceApi": "https://terraria.wiki.gg/api.php",
    "sourceFile": "terraPedia/data/raw/wiki/item-pages/woodplatform.latest.json",
    "wikitextLength": 410
  },
  {
    "entityType": "item",
    "fetchedAt": "2026-03-28T02:10:05.192Z",
    "hasHtml": true,
    "hasRecipesMarkup": true,
    "hasWikitext": true,
    "htmlLength": 1518,
    "itemInternalName": "WoodShelf",
    "itemName": "Wood Shelf",
    "pageId": 13781,
    "pageTitle": "Wood Shelf",
    "recipesMarkupLength": 0,
    "requestedPageTitle": "Wood Shelf",
    "revisionTimestamp": "2025-07-24T10:45:25Z",
    "sourceApi": "https://terraria.wiki.gg/api.php",
    "sourceFile": "terraPedia/data/raw/wiki/item-pages/woodshelf.latest.json",
    "wikitextLength": 573
  },
  {
    "entityType": "item",
    "fetchedAt": "2026-03-28T01:06:48.573Z",
    "hasHtml": true,
    "hasRecipesMarkup": true,
    "hasWikitext": true,
    "htmlLength": 123599,
    "itemInternalName": "WoodWall",
    "itemName": "Wood Wall",
    "pageId": 8451,
    "pageTitle": "Wood Wall",
    "recipesMarkupLength": 723,
    "requestedPageTitle": "Wood Wall",
    "revisionTimestamp": "2025-11-14T06:32:40Z",
    "sourceApi": "https://terraria.wiki.gg/api.php",
    "sourceFile": "terraPedia/data/raw/wiki/item-pages/woodwall.latest.json",
    "wikitextLength": 810
  },
  {
    "entityType": "item",
    "fetchedAt": "2026-03-28T03:13:17.299Z",
    "hasHtml": true,
    "hasRecipesMarkup": true,
    "hasWikitext": true,
    "htmlLength": 125416,
    "itemInternalName": "WoodYoyo",
    "itemName": "Wooden Yoyo",
    "pageId": 12619,
    "pageTitle": "Wooden Yoyo",
    "recipesMarkupLength": 1029,
    "requestedPageTitle": "Wooden Yoyo",
    "revisionTimestamp": "2026-03-22T06:02:10Z",
    "sourceApi": "https://terraria.wiki.gg/api.php",
    "sourceFile": "terraPedia/data/raw/wiki/item-pages/woodyoyo.latest.json",
    "wikitextLength": 1250
  },
  {
    "entityType": "item",
    "fetchedAt": "2026-03-27T11:14:20.763Z",
    "hasHtml": true,
    "hasRecipesMarkup": true,
    "hasWikitext": true,
    "htmlLength": 1479,
    "itemInternalName": "WorkBench",
    "itemName": "Work Bench",
    "pageId": 13787,
    "pageTitle": "Work Bench",
    "recipesMarkupLength": 0,
    "requestedPageTitle": "Work Bench",
    "revisionTimestamp": "2025-07-24T10:45:47Z",
    "sourceApi": "https://terraria.wiki.gg/api.php",
    "sourceFile": "terraPedia/data/raw/wiki/item-pages/workbench.latest.json",
    "wikitextLength": 377
  },
  {
    "entityType": "item",
    "fetchedAt": "2026-03-28T01:51:40.483Z",
    "hasHtml": true,
    "hasRecipesMarkup": true,
    "hasWikitext": true,
    "htmlLength": 1503,
    "itemInternalName": "WorldBanner",
    "itemName": "World Banner",
    "pageId": 15526,
    "pageTitle": "World Banner",
    "recipesMarkupLength": 0,
    "requestedPageTitle": "World Banner",
    "revisionTimestamp": "2025-07-23T18:42:01Z",
    "sourceApi": "https://terraria.wiki.gg/api.php",
    "sourceFile": "terraPedia/data/raw/wiki/item-pages/worldbanner.latest.json",
    "wikitextLength": 275
  },
  {
    "entityType": "item",
    "fetchedAt": "2026-03-28T02:18:45.430Z",
    "hasHtml": true,
    "hasRecipesMarkup": true,
    "hasWikitext": true,
    "htmlLength": 1416,
    "itemInternalName": "WorldFeederBanner",
    "itemName": "World Feeder Banner",
    "pageId": 4076,
    "pageTitle": "World Feeder Banner",
    "recipesMarkupLength": 0,
    "requestedPageTitle": "World Feeder Banner",
    "revisionTimestamp": "2025-07-24T10:45:52Z",
    "sourceApi": "https://terraria.wiki.gg/api.php",
    "sourceFile": "terraPedia/data/raw/wiki/item-pages/worldfeederbanner.latest.json",
    "wikitextLength": 203
  },
  {
    "entityType": "item",
    "fetchedAt": "2026-03-28T04:08:03.785Z",
    "hasHtml": true,
    "hasRecipesMarkup": true,
    "hasWikitext": true,
    "htmlLength": 150190,
    "itemInternalName": "WorldGlobe",
    "itemName": "World Globe",
    "pageId": 7768,
    "pageTitle": "World Globe",
    "recipesMarkupLength": 0,
    "requestedPageTitle": "World Globe",
    "revisionTimestamp": "2026-01-31T14:49:20Z",
    "sourceApi": "https://terraria.wiki.gg/api.php",
    "sourceFile": "terraPedia/data/raw/wiki/item-pages/worldglobe.latest.json",
    "wikitextLength": 3865
  },
  {
    "entityType": "item",
    "fetchedAt": "2026-03-28T02:28:31.441Z",
    "hasHtml": true,
    "hasRecipesMarkup": true,
    "hasWikitext": true,
    "htmlLength": 166936,
    "itemInternalName": "Worm",
    "itemName": "Worm",
    "pageId": 10526,
    "pageTitle": "Worm",
    "recipesMarkupLength": 0,
    "requestedPageTitle": "Worm",
    "revisionTimestamp": "2026-03-22T04:32:46Z",
    "sourceApi": "https://terraria.wiki.gg/api.php",
    "sourceFile": "terraPedia/data/raw/wiki/item-pages/worm.latest.json",
    "wikitextLength": 8280
  },
  {
    "entityType": "item",
    "fetchedAt": "2026-03-28T02:18:47.119Z",
    "hasHtml": true,
    "hasRecipesMarkup": true,
    "hasWikitext": true,
    "htmlLength": 1401,
    "itemInternalName": "WormBanner",
    "itemName": "Worm Banner",
    "pageId": 10684,
    "pageTitle": "Worm Banner",
    "recipesMarkupLength": 0,
    "requestedPageTitle": "Worm Banner",
    "revisionTimestamp": "2025-07-24T10:46:01Z",
    "sourceApi": "https://terraria.wiki.gg/api.php",
    "sourceFile": "terraPedia/data/raw/wiki/item-pages/wormbanner.latest.json",
    "wikitextLength": 163
  },
  {
    "entityType": "item",
    "fetchedAt": "2026-03-28T02:34:24.150Z",
    "hasHtml": true,
    "hasRecipesMarkup": true,
    "hasWikitext": true,
    "htmlLength": 1075,
    "itemInternalName": "WormCage",
    "itemName": "Worm Cage",
    "pageId": 5533,
    "pageTitle": "Worm Cage",
    "recipesMarkupLength": 0,
    "requestedPageTitle": "Worm Cage",
    "revisionTimestamp": "2025-07-24T22:59:59Z",
    "sourceApi": "https://terraria.wiki.gg/api.php",
    "sourceFile": "terraPedia/data/raw/wiki/item-pages/wormcage.latest.json",
    "wikitextLength": 69
  },
  {
    "entityType": "item",
    "fetchedAt": "2026-03-28T01:06:38.517Z",
    "hasHtml": true,
    "hasRecipesMarkup": true,
    "hasWikitext": true,
    "htmlLength": 139799,
    "itemInternalName": "WormFood",
    "itemName": "Worm Food",
    "pageId": 13960,
    "pageTitle": "Worm Food",
    "recipesMarkupLength": 1059,
    "requestedPageTitle": "Worm Food",
    "revisionTimestamp": "2025-03-02T13:14:07Z",
    "sourceApi": "https://terraria.wiki.gg/api.php",
    "sourceFile": "terraPedia/data/raw/wiki/item-pages/wormfood.latest.json",
    "wikitextLength": 1213
  },
  {
    "entityType": "item",
    "fetchedAt": "2026-03-28T03:02:58.245Z",
    "hasHtml": true,
    "hasRecipesMarkup": true,
    "hasWikitext": true,
    "htmlLength": 145269,
    "itemInternalName": "WormholePotion",
    "itemName": "Wormhole Potion",
    "pageId": 9797,
    "pageTitle": "Wormhole Potion",
    "recipesMarkupLength": 1819,
    "requestedPageTitle": "Wormhole Potion",
    "revisionTimestamp": "2026-02-16T18:54:32Z",
    "sourceApi": "https://terraria.wiki.gg/api.php",
    "sourceFile": "terraPedia/data/raw/wiki/item-pages/wormholepotion.latest.json",
    "wikitextLength": 2329
  },
  {
    "entityType": "item",
    "fetchedAt": "2026-03-28T03:04:03.207Z",
    "hasHtml": true,
    "hasRecipesMarkup": true,
    "hasWikitext": true,
    "htmlLength": 1690,
    "itemInternalName": "WormHook",
    "itemName": "Worm Hook",
    "pageId": 4180,
    "pageTitle": "Worm Hook",
    "recipesMarkupLength": 0,
    "requestedPageTitle": "Worm Hook",
    "revisionTimestamp": "2025-07-24T10:46:05Z",
    "sourceApi": "https://terraria.wiki.gg/api.php",
    "sourceFile": "terraPedia/data/raw/wiki/item-pages/wormhook.latest.json",
    "wikitextLength": 340
  },
  {
    "entityType": "item",
    "fetchedAt": "2026-03-28T03:11:21.574Z",
    "hasHtml": true,
    "hasRecipesMarkup": true,
    "hasWikitext": true,
    "htmlLength": 189021,
    "itemInternalName": "WormScarf",
    "itemName": "Worm Scarf",
    "pageId": 8521,
    "pageTitle": "Worm Scarf",
    "recipesMarkupLength": 0,
    "requestedPageTitle": "Worm Scarf",
    "revisionTimestamp": "2026-02-01T14:37:36Z",
    "sourceApi": "https://terraria.wiki.gg/api.php",
    "sourceFile": "terraPedia/data/raw/wiki/item-pages/wormscarf.latest.json",
    "wikitextLength": 2007
  },
  {
    "entityType": "item",
    "fetchedAt": "2026-03-28T03:28:25.742Z",
    "hasHtml": true,
    "hasRecipesMarkup": true,
    "hasWikitext": true,
    "htmlLength": 1734,
    "itemInternalName": "WormStatue",
    "itemName": "Worm Statue",
    "pageId": 7401,
    "pageTitle": "Worm Statue",
    "recipesMarkupLength": 0,
    "requestedPageTitle": "Worm Statue",
    "revisionTimestamp": "2026-01-29T14:59:37Z",
    "sourceApi": "https://terraria.wiki.gg/api.php",
    "sourceFile": "terraPedia/data/raw/wiki/item-pages/wormstatue.latest.json",
    "wikitextLength": 317
  },
  {
    "entityType": "item",
    "fetchedAt": "2026-03-28T01:06:38.285Z",
    "hasHtml": true,
    "hasRecipesMarkup": true,
    "hasWikitext": true,
    "htmlLength": 145104,
    "itemInternalName": "WormTooth",
    "itemName": "Worm Tooth",
    "pageId": 12459,
    "pageTitle": "Worm Tooth",
    "recipesMarkupLength": 0,
    "requestedPageTitle": "Worm Tooth",
    "revisionTimestamp": "2025-02-11T03:08:32Z",
    "sourceApi": "https://terraria.wiki.gg/api.php",
    "sourceFile": "terraPedia/data/raw/wiki/item-pages/wormtooth.latest.json",
    "wikitextLength": 1498
  },
  {
    "entityType": "item",
    "fetchedAt": "2026-03-28T02:18:48.416Z",
    "hasHtml": true,
    "hasRecipesMarkup": true,
    "hasWikitext": true,
    "htmlLength": 1405,
    "itemInternalName": "WraithBanner",
    "itemName": "Wraith Banner",
    "pageId": 14511,
    "pageTitle": "Wraith Banner",
    "recipesMarkupLength": 0,
    "requestedPageTitle": "Wraith Banner",
    "revisionTimestamp": "2025-07-24T10:46:33Z",
    "sourceApi": "https://terraria.wiki.gg/api.php",
    "sourceFile": "terraPedia/data/raw/wiki/item-pages/wraithbanner.latest.json",
    "wikitextLength": 198
  },
  {
    "entityType": "item",
    "fetchedAt": "2026-03-28T03:30:16.653Z",
    "hasHtml": true,
    "hasRecipesMarkup": true,
    "hasWikitext": true,
    "htmlLength": 1739,
    "itemInternalName": "WraithStatue",
    "itemName": "Wraith Statue",
    "pageId": 12791,
    "pageTitle": "Wraith Statue",
    "recipesMarkupLength": 0,
    "requestedPageTitle": "Wraith Statue",
    "revisionTimestamp": "2025-07-24T10:46:37Z",
    "sourceApi": "https://terraria.wiki.gg/api.php",
    "sourceFile": "terraPedia/data/raw/wiki/item-pages/wraithstatue.latest.json",
    "wikitextLength": 274
  },
  {
    "entityType": "item",
    "fetchedAt": "2026-03-28T02:39:56.236Z",
    "hasHtml": true,
    "hasRecipesMarkup": true,
    "hasWikitext": true,
    "htmlLength": 287297,
    "itemInternalName": "WrathPotion",
    "itemName": "Wrath Potion",
    "pageId": 7683,
    "pageTitle": "Wrath Potion",
    "recipesMarkupLength": 1583,
    "requestedPageTitle": "Wrath Potion",
    "revisionTimestamp": "2025-08-25T14:29:33Z",
    "sourceApi": "https://terraria.wiki.gg/api.php",
    "sourceFile": "terraPedia/data/raw/wiki/item-pages/wrathpotion.latest.json",
    "wikitextLength": 982
  },
  {
    "entityType": "item",
    "fetchedAt": "2026-03-28T01:39:37.817Z",
    "hasHtml": true,
    "hasRecipesMarkup": true,
    "hasWikitext": true,
    "htmlLength": 1084,
    "itemInternalName": "Wrench",
    "itemName": "Red Wrench",
    "pageId": 9614,
    "pageTitle": "Red Wrench",
    "recipesMarkupLength": 0,
    "requestedPageTitle": "Red Wrench",
    "revisionTimestamp": "2025-07-23T06:55:29Z",
    "sourceApi": "https://terraria.wiki.gg/api.php",
    "sourceFile": "terraPedia/data/raw/wiki/item-pages/wrench.latest.json",
    "wikitextLength": 77
  },
  {
    "entityType": "item",
    "fetchedAt": "2026-03-28T03:56:31.471Z",
    "hasHtml": true,
    "hasRecipesMarkup": true,
    "hasWikitext": true,
    "htmlLength": 1674,
    "itemInternalName": "WroughtIronFence",
    "itemName": "Wrought Iron Fence",
    "pageId": 15886,
    "pageTitle": "Wrought Iron Fence",
    "recipesMarkupLength": 0,
    "requestedPageTitle": "Wrought Iron Fence",
    "revisionTimestamp": "2026-01-29T14:59:37Z",
    "sourceApi": "https://terraria.wiki.gg/api.php",
    "sourceFile": "terraPedia/data/raw/wiki/item-pages/wroughtironfence.latest.json",
    "wikitextLength": 127
  },
  {
    "entityType": "item",
    "fetchedAt": "2026-03-28T02:18:49.891Z",
    "hasHtml": true,
    "hasRecipesMarkup": true,
    "hasWikitext": true,
    "htmlLength": 1404,
    "itemInternalName": "WyvernBanner",
    "itemName": "Wyvern Banner",
    "pageId": 8984,
    "pageTitle": "Wyvern Banner",
    "recipesMarkupLength": 0,
    "requestedPageTitle": "Wyvern Banner",
    "revisionTimestamp": "2025-07-24T10:46:42Z",
    "sourceApi": "https://terraria.wiki.gg/api.php",
    "sourceFile": "terraPedia/data/raw/wiki/item-pages/wyvernbanner.latest.json",
    "wikitextLength": 198
  },
  {
    "entityType": "item",
    "fetchedAt": "2026-03-28T02:43:56.658Z",
    "hasHtml": true,
    "hasRecipesMarkup": true,
    "hasWikitext": true,
    "htmlLength": 1393,
    "itemInternalName": "Wyverntail",
    "itemName": "Wyverntail",
    "pageId": 13567,
    "pageTitle": "Wyverntail",
    "recipesMarkupLength": 0,
    "requestedPageTitle": "Wyverntail",
    "revisionTimestamp": "2025-07-24T23:00:03Z",
    "sourceApi": "https://terraria.wiki.gg/api.php",
    "sourceFile": "terraPedia/data/raw/wiki/item-pages/wyverntail.latest.json",
    "wikitextLength": 195
  },
  {
    "entityType": "item",
    "fetchedAt": "2026-03-28T03:54:55.971Z",
    "hasHtml": true,
    "hasRecipesMarkup": true,
    "hasWikitext": true,
    "htmlLength": 1667,
    "itemInternalName": "XenonMoss",
    "itemName": "Xenon Moss",
    "pageId": 8127,
    "pageTitle": "Xenon Moss",
    "recipesMarkupLength": 0,
    "requestedPageTitle": "Xenon Moss",
    "revisionTimestamp": "2025-07-23T04:34:05Z",
    "sourceApi": "https://terraria.wiki.gg/api.php",
    "sourceFile": "terraPedia/data/raw/wiki/item-pages/xenonmoss.latest.json",
    "wikitextLength": 138
  },
  {
    "entityType": "item",
    "fetchedAt": "2026-03-28T04:37:14.048Z",
    "hasHtml": true,
    "hasRecipesMarkup": true,
    "hasWikitext": true,
    "htmlLength": 123176,
    "itemInternalName": "XenonMossBlock",
    "itemName": "Xenon Moss Brick",
    "pageId": 60230,
    "pageTitle": "Xenon Moss Brick",
    "recipesMarkupLength": 2129,
    "requestedPageTitle": "Xenon Moss Brick",
    "revisionTimestamp": "2026-03-27T06:43:46Z",
    "sourceApi": "https://terraria.wiki.gg/api.php",
    "sourceFile": "terraPedia/data/raw/wiki/item-pages/xenonmossblock.latest.json",
    "wikitextLength": 581
  },
  {
    "entityType": "item",
    "fetchedAt": "2026-03-28T04:37:38.225Z",
    "hasHtml": true,
    "hasRecipesMarkup": true,
    "hasWikitext": true,
    "htmlLength": 125640,
    "itemInternalName": "XenonMossBlockWall",
    "itemName": "Xenon Moss Brick Wall",
    "pageId": 60236,
    "pageTitle": "Xenon Moss Brick Wall",
    "recipesMarkupLength": 1125,
    "requestedPageTitle": "Xenon Moss Brick Wall",
    "revisionTimestamp": "2026-03-27T06:44:16Z",
    "sourceApi": "https://terraria.wiki.gg/api.php",
    "sourceFile": "terraPedia/data/raw/wiki/item-pages/xenonmossblockwall.latest.json",
    "wikitextLength": 640
  },
  {
    "entityType": "item",
    "fetchedAt": "2026-03-28T02:55:47.238Z",
    "hasHtml": true,
    "hasRecipesMarkup": true,
    "hasWikitext": true,
    "htmlLength": 116134,
    "itemInternalName": "Xenopopper",
    "itemName": "Xenopopper",
    "pageId": 10518,
    "pageTitle": "Xenopopper",
    "recipesMarkupLength": 0,
    "requestedPageTitle": "Xenopopper",
    "revisionTimestamp": "2026-01-10T20:44:23Z",
    "sourceApi": "https://terraria.wiki.gg/api.php",
    "sourceFile": "terraPedia/data/raw/wiki/item-pages/xenopopper.latest.json",
    "wikitextLength": 1990
  },
  {
    "entityType": "item",
    "fetchedAt": "2026-03-28T02:53:46.781Z",
    "hasHtml": true,
    "hasRecipesMarkup": true,
    "hasWikitext": true,
    "htmlLength": 288917,
    "itemInternalName": "XenoStaff",
    "itemName": "Xeno Staff",
    "pageId": 4772,
    "pageTitle": "Xeno Staff",
    "recipesMarkupLength": 0,
    "requestedPageTitle": "Xeno Staff",
    "revisionTimestamp": "2026-02-12T10:49:11Z",
    "sourceApi": "https://terraria.wiki.gg/api.php",
    "sourceFile": "terraPedia/data/raw/wiki/item-pages/xenostaff.latest.json",
    "wikitextLength": 3444
  },
  {
    "entityType": "item",
    "fetchedAt": "2026-03-28T03:13:43.406Z",
    "hasHtml": true,
    "hasRecipesMarkup": true,
    "hasWikitext": true,
    "htmlLength": 120362,
    "itemInternalName": "Yelets",
    "itemName": "Yelets",
    "pageId": 8223,
    "pageTitle": "Yelets",
    "recipesMarkupLength": 0,
    "requestedPageTitle": "Yelets",
    "revisionTimestamp": "2026-03-22T06:09:42Z",
    "sourceApi": "https://terraria.wiki.gg/api.php",
    "sourceFile": "terraPedia/data/raw/wiki/item-pages/yelets.latest.json",
    "wikitextLength": 1607
  },
  {
    "entityType": "item",
    "fetchedAt": "2026-03-28T01:57:28.995Z",
    "hasHtml": true,
    "hasRecipesMarkup": true,
    "hasWikitext": true,
    "htmlLength": 1709,
    "itemInternalName": "YellowandBlackDye",
    "itemName": "Yellow and Black Dye",
    "pageId": 11152,
    "pageTitle": "Yellow and Black Dye",
    "recipesMarkupLength": 0,
    "requestedPageTitle": "Yellow and Black Dye",
    "revisionTimestamp": "2025-07-24T10:46:50Z",
    "sourceApi": "https://terraria.wiki.gg/api.php",
    "sourceFile": "terraPedia/data/raw/wiki/item-pages/yellowandblackdye.latest.json",
    "wikitextLength": 122
  },
  {
    "entityType": "item",
    "fetchedAt": "2026-03-28T02:24:51.190Z",
    "hasHtml": true,
    "hasRecipesMarkup": true,
    "hasWikitext": true,
    "htmlLength": 1778,
    "itemInternalName": "YellowAndGreenBulb",
    "itemName": "Yellow and Green Bulb",
    "pageId": 11235,
    "pageTitle": "Yellow and Green Bulb",
    "recipesMarkupLength": 0,
    "requestedPageTitle": "Yellow and Green Bulb",
    "revisionTimestamp": "2025-07-24T10:46:55Z",
    "sourceApi": "https://terraria.wiki.gg/api.php",
    "sourceFile": "terraPedia/data/raw/wiki/item-pages/yellowandgreenbulb.latest.json",
    "wikitextLength": 169
  },
  {
    "entityType": "item",
    "fetchedAt": "2026-03-28T02:25:13.056Z",
    "hasHtml": true,
    "hasRecipesMarkup": true,
    "hasWikitext": true,
    "htmlLength": 1782,
    "itemInternalName": "YellowAndGreenLights",
    "itemName": "Yellow and Green Lights",
    "pageId": 10863,
    "pageTitle": "Yellow and Green Lights",
    "recipesMarkupLength": 0,
    "requestedPageTitle": "Yellow and Green Lights",
    "revisionTimestamp": "2025-07-24T10:46:59Z",
    "sourceApi": "https://terraria.wiki.gg/api.php",
    "sourceFile": "terraPedia/data/raw/wiki/item-pages/yellowandgreenlights.latest.json",
    "wikitextLength": 171
  },
  {
    "entityType": "item",
    "fetchedAt": "2026-03-28T01:58:21.406Z",
    "hasHtml": true,
    "hasRecipesMarkup": true,
    "hasWikitext": true,
    "htmlLength": 1710,
    "itemInternalName": "YellowandSilverDye",
    "itemName": "Yellow and Silver Dye",
    "pageId": 5293,
    "pageTitle": "Yellow and Silver Dye",
    "recipesMarkupLength": 0,
    "requestedPageTitle": "Yellow and Silver Dye",
    "revisionTimestamp": "2025-07-24T10:47:03Z",
    "sourceApi": "https://terraria.wiki.gg/api.php",
    "sourceFile": "terraPedia/data/raw/wiki/item-pages/yellowandsilverdye.latest.json",
    "wikitextLength": 123
  },
  {
    "entityType": "item",
    "fetchedAt": "2026-03-28T01:16:01.805Z",
    "hasHtml": true,
    "hasRecipesMarkup": true,
    "hasWikitext": true,
    "htmlLength": 1137,
    "itemInternalName": "YellowBanner",
    "itemName": "Yellow Banner",
    "pageId": 11869,
    "pageTitle": "Yellow Banner",
    "recipesMarkupLength": 0,
    "requestedPageTitle": "Yellow Banner",
    "revisionTimestamp": "2025-07-23T18:43:01Z",
    "sourceApi": "https://terraria.wiki.gg/api.php",
    "sourceFile": "terraPedia/data/raw/wiki/item-pages/yellowbanner.latest.json",
    "wikitextLength": 89
  },
  {
    "entityType": "item",
    "fetchedAt": "2026-03-28T02:24:45.886Z",
    "hasHtml": true,
    "hasRecipesMarkup": true,
    "hasWikitext": true,
    "htmlLength": 1757,
    "itemInternalName": "YellowBulb",
    "itemName": "Yellow Bulb",
    "pageId": 4227,
    "pageTitle": "Yellow Bulb",
    "recipesMarkupLength": 0,
    "requestedPageTitle": "Yellow Bulb",
    "revisionTimestamp": "2025-07-24T10:47:08Z",
    "sourceApi": "https://terraria.wiki.gg/api.php",
    "sourceFile": "terraPedia/data/raw/wiki/item-pages/yellowbulb.latest.json",
    "wikitextLength": 159
  },
  {
    "entityType": "item",
    "fetchedAt": "2026-03-28T04:30:22.883Z",
    "hasHtml": true,
    "hasRecipesMarkup": true,
    "hasWikitext": true,
    "htmlLength": 1685,
    "itemInternalName": "YellowCockatiel",
    "itemName": "Yellow Cockatiel",
    "pageId": 59707,
    "pageTitle": "Yellow Cockatiel",
    "recipesMarkupLength": 0,
    "requestedPageTitle": "Yellow Cockatiel",
    "revisionTimestamp": "2026-03-06T18:05:25Z",
    "sourceApi": "https://terraria.wiki.gg/api.php",
    "sourceFile": "terraPedia/data/raw/wiki/item-pages/yellowcockatiel.latest.json",
    "wikitextLength": 117
  },
  {
    "entityType": "item",
    "fetchedAt": "2026-03-28T04:30:28.347Z",
    "hasHtml": true,
    "hasRecipesMarkup": true,
    "hasWikitext": true,
    "htmlLength": 1670,
    "itemInternalName": "YellowCockatielCage",
    "itemName": "Yellow Cockatiel Cage",
    "pageId": 59700,
    "pageTitle": "Yellow Cockatiel Cage",
    "recipesMarkupLength": 0,
    "requestedPageTitle": "Yellow Cockatiel Cage",
    "revisionTimestamp": "2025-11-20T16:16:30Z",
    "sourceApi": "https://terraria.wiki.gg/api.php",
    "sourceFile": "terraPedia/data/raw/wiki/item-pages/yellowcockatielcage.latest.json",
    "wikitextLength": 113
  },
  {
    "entityType": "item",
    "fetchedAt": "2026-03-28T03:14:33.173Z",
    "hasHtml": true,
    "hasRecipesMarkup": true,
    "hasWikitext": true,
    "htmlLength": 1698,
    "itemInternalName": "YellowCounterweight",
    "itemName": "Yellow Counterweight",
    "pageId": 13441,
    "pageTitle": "Yellow Counterweight",
    "recipesMarkupLength": 0,
    "requestedPageTitle": "Yellow Counterweight",
    "revisionTimestamp": "2025-07-24T10:47:21Z",
    "sourceApi": "https://terraria.wiki.gg/api.php",
    "sourceFile": "terraPedia/data/raw/wiki/item-pages/yellowcounterweight.latest.json",
    "wikitextLength": 338
  },
  {
    "entityType": "item",
    "fetchedAt": "2026-03-28T03:53:43.307Z",
    "hasHtml": true,
    "hasRecipesMarkup": true,
    "hasWikitext": true,
    "htmlLength": 1688,
    "itemInternalName": "YellowDragonfly",
    "itemName": "Yellow Dragonfly",
    "pageId": 12382,
    "pageTitle": "Yellow Dragonfly",
    "recipesMarkupLength": 0,
    "requestedPageTitle": "Yellow Dragonfly",
    "revisionTimestamp": "2025-07-23T18:37:10Z",
    "sourceApi": "https://terraria.wiki.gg/api.php",
    "sourceFile": "terraPedia/data/raw/wiki/item-pages/yellowdragonfly.latest.json",
    "wikitextLength": 93
  },
  {
    "entityType": "item",
    "fetchedAt": "2026-03-28T03:53:30.538Z",
    "hasHtml": true,
    "hasRecipesMarkup": true,
    "hasWikitext": true,
    "htmlLength": 1697,
    "itemInternalName": "YellowDragonflyJar",
    "itemName": "Yellow Dragonfly Jar",
    "pageId": 15692,
    "pageTitle": "Yellow Dragonfly Jar",
    "recipesMarkupLength": 0,
    "requestedPageTitle": "Yellow Dragonfly Jar",
    "revisionTimestamp": "2025-07-23T18:35:38Z",
    "sourceApi": "https://terraria.wiki.gg/api.php",
    "sourceFile": "terraPedia/data/raw/wiki/item-pages/yellowdragonflyjar.latest.json",
    "wikitextLength": 120
  },
  {
    "entityType": "item",
    "fetchedAt": "2026-03-28T01:57:09.499Z",
    "hasHtml": true,
    "hasRecipesMarkup": true,
    "hasWikitext": true,
    "htmlLength": 1688,
    "itemInternalName": "YellowDye",
    "itemName": "Yellow Dye",
    "pageId": 8466,
    "pageTitle": "Yellow Dye",
    "recipesMarkupLength": 0,
    "requestedPageTitle": "Yellow Dye",
    "revisionTimestamp": "2025-07-24T10:47:25Z",
    "sourceApi": "https://terraria.wiki.gg/api.php",
    "sourceFile": "terraPedia/data/raw/wiki/item-pages/yellowdye.latest.json",
    "wikitextLength": 112
  },
  {
    "entityType": "item",
    "fetchedAt": "2026-03-28T01:58:45.011Z",
    "hasHtml": true,
    "hasRecipesMarkup": true,
    "hasWikitext": true,
    "htmlLength": 1707,
    "itemInternalName": "YellowGradientDye",
    "itemName": "Yellow Gradient Dye",
    "pageId": 12409,
    "pageTitle": "Yellow Gradient Dye",
    "recipesMarkupLength": 0,
    "requestedPageTitle": "Yellow Gradient Dye",
    "revisionTimestamp": "2025-07-24T10:47:39Z",
    "sourceApi": "https://terraria.wiki.gg/api.php",
    "sourceFile": "terraPedia/data/raw/wiki/item-pages/yellowgradientdye.latest.json",
    "wikitextLength": 121
  },
  {
    "entityType": "item",
    "fetchedAt": "2026-03-28T02:05:17.529Z",
    "hasHtml": true,
    "hasRecipesMarkup": true,
    "hasWikitext": true,
    "htmlLength": 214830,
    "itemInternalName": "YellowHorseshoeBalloon",
    "itemName": "Yellow Horseshoe Balloon",
    "pageId": 10341,
    "pageTitle": "Yellow Horseshoe Balloon",
    "recipesMarkupLength": 1023,
    "requestedPageTitle": "Yellow Horseshoe Balloon",
    "revisionTimestamp": "2026-02-01T12:46:05Z",
    "sourceApi": "https://terraria.wiki.gg/api.php",
    "sourceFile": "terraPedia/data/raw/wiki/item-pages/yellowhorseshoeballoon.latest.json",
    "wikitextLength": 2943
  },
  {
    "entityType": "item",
    "fetchedAt": "2026-03-28T02:25:08.059Z",
    "hasHtml": true,
    "hasRecipesMarkup": true,
    "hasWikitext": true,
    "htmlLength": 1762,
    "itemInternalName": "YellowLights",
    "itemName": "Yellow Lights",
    "pageId": 10869,
    "pageTitle": "Yellow Lights",
    "recipesMarkupLength": 0,
    "requestedPageTitle": "Yellow Lights",
    "revisionTimestamp": "2025-07-24T10:47:48Z",
    "sourceApi": "https://terraria.wiki.gg/api.php",
    "sourceFile": "terraPedia/data/raw/wiki/item-pages/yellowlights.latest.json",
    "wikitextLength": 161
  },
  {
    "entityType": "item",
    "fetchedAt": "2026-03-28T02:00:05.218Z",
    "hasHtml": true,
    "hasRecipesMarkup": true,
    "hasWikitext": true,
    "htmlLength": 153007,
    "itemInternalName": "YellowMarigold",
    "itemName": "Yellow Marigold",
    "pageId": 15461,
    "pageTitle": "Yellow Marigold",
    "recipesMarkupLength": 0,
    "requestedPageTitle": "Yellow Marigold",
    "revisionTimestamp": "2026-03-01T09:34:16Z",
    "sourceApi": "https://terraria.wiki.gg/api.php",
    "sourceFile": "terraPedia/data/raw/wiki/item-pages/yellowmarigold.latest.json",
    "wikitextLength": 1861
  },
  {
    "entityType": "item",
    "fetchedAt": "2026-03-28T01:59:00.137Z",
    "hasHtml": true,
    "hasRecipesMarkup": true,
    "hasWikitext": true,
    "htmlLength": 1673,
    "itemInternalName": "YellowPaint",
    "itemName": "Yellow Paint",
    "pageId": 11940,
    "pageTitle": "Yellow Paint",
    "recipesMarkupLength": 0,
    "requestedPageTitle": "Yellow Paint",
    "revisionTimestamp": "2025-07-24T10:47:52Z",
    "sourceApi": "https://terraria.wiki.gg/api.php",
    "sourceFile": "terraPedia/data/raw/wiki/item-pages/yellowpaint.latest.json",
    "wikitextLength": 110
  },
  {
    "entityType": "item",
    "fetchedAt": "2026-03-28T01:31:31.479Z",
    "hasHtml": true,
    "hasRecipesMarkup": true,
    "hasWikitext": true,
    "htmlLength": 1095,
    "itemInternalName": "YellowPhaseblade",
    "itemName": "Yellow Phaseblade",
    "pageId": 15157,
    "pageTitle": "Yellow Phaseblade",
    "recipesMarkupLength": 0,
    "requestedPageTitle": "Yellow Phaseblade",
    "revisionTimestamp": "2025-07-23T06:58:57Z",
    "sourceApi": "https://terraria.wiki.gg/api.php",
    "sourceFile": "terraPedia/data/raw/wiki/item-pages/yellowphaseblade.latest.json",
    "wikitextLength": 138
  },
  {
    "entityType": "item",
    "fetchedAt": "2026-03-28T03:32:29.401Z",
    "hasHtml": true,
    "hasRecipesMarkup": true,
    "hasWikitext": true,
    "htmlLength": 1095,
    "itemInternalName": "YellowPhasesaber",
    "itemName": "Yellow Phasesaber",
    "pageId": 11250,
    "pageTitle": "Yellow Phasesaber",
    "recipesMarkupLength": 0,
    "requestedPageTitle": "Yellow Phasesaber",
    "revisionTimestamp": "2025-07-23T06:59:15Z",
    "sourceApi": "https://terraria.wiki.gg/api.php",
    "sourceFile": "terraPedia/data/raw/wiki/item-pages/yellowphasesaber.latest.json",
    "wikitextLength": 208
  },
  {
    "entityType": "item",
    "fetchedAt": "2026-03-28T01:42:49.724Z",
    "hasHtml": true,
    "hasRecipesMarkup": true,
    "hasWikitext": true,
    "htmlLength": 1082,
    "itemInternalName": "YellowPresent",
    "itemName": "Yellow Present",
    "pageId": 15328,
    "pageTitle": "Yellow Present",
    "recipesMarkupLength": 0,
    "requestedPageTitle": "Yellow Present",
    "revisionTimestamp": "2025-07-24T10:47:57Z",
    "sourceApi": "https://terraria.wiki.gg/api.php",
    "sourceFile": "terraPedia/data/raw/wiki/item-pages/yellowpresent.latest.json",
    "wikitextLength": 49
  },
  {
    "entityType": "item",
    "fetchedAt": "2026-03-28T01:51:53.076Z",
    "hasHtml": true,
    "hasRecipesMarkup": true,
    "hasWikitext": true,
    "htmlLength": 1149,
    "itemInternalName": "YellowPressurePlate",
    "itemName": "Yellow Pressure Plate",
    "pageId": 8889,
    "pageTitle": "Yellow Pressure Plate",
    "recipesMarkupLength": 0,
    "requestedPageTitle": "Yellow Pressure Plate",
    "revisionTimestamp": "2025-07-23T06:03:40Z",
    "sourceApi": "https://terraria.wiki.gg/api.php",
    "sourceFile": "terraPedia/data/raw/wiki/item-pages/yellowpressureplate.latest.json",
    "wikitextLength": 135
  },
  {
    "entityType": "item",
    "fetchedAt": "2026-03-28T01:55:47.741Z",
    "hasHtml": true,
    "hasRecipesMarkup": true,
    "hasWikitext": true,
    "htmlLength": 1108,
    "itemInternalName": "YellowRocket",
    "itemName": "Yellow Rocket",
    "pageId": 7851,
    "pageTitle": "Yellow Rocket",
    "recipesMarkupLength": 0,
    "requestedPageTitle": "Yellow Rocket",
    "revisionTimestamp": "2025-07-23T07:26:27Z",
    "sourceApi": "https://terraria.wiki.gg/api.php",
    "sourceFile": "terraPedia/data/raw/wiki/item-pages/yellowrocket.latest.json",
    "wikitextLength": 113
  },
  {
    "entityType": "item",
    "fetchedAt": "2026-03-28T03:02:45.814Z",
    "hasHtml": true,
    "hasRecipesMarkup": true,
    "hasWikitext": true,
    "htmlLength": 1740,
    "itemInternalName": "YellowSlimeBanner",
    "itemName": "Yellow Slime Banner",
    "pageId": 8873,
    "pageTitle": "Yellow Slime Banner",
    "recipesMarkupLength": 0,
    "requestedPageTitle": "Yellow Slime Banner",
    "revisionTimestamp": "2025-07-24T23:00:08Z",
    "sourceApi": "https://terraria.wiki.gg/api.php",
    "sourceFile": "terraPedia/data/raw/wiki/item-pages/yellowslimebanner.latest.json",
    "wikitextLength": 271
  },
  {
    "entityType": "item",
    "fetchedAt": "2026-03-28T02:05:52.319Z",
    "hasHtml": true,
    "hasRecipesMarkup": true,
    "hasWikitext": true,
    "htmlLength": 1100,
    "itemInternalName": "YellowStainedGlass",
    "itemName": "Yellow Stained Glass",
    "pageId": 10280,
    "pageTitle": "Yellow Stained Glass",
    "recipesMarkupLength": 0,
    "requestedPageTitle": "Yellow Stained Glass",
    "revisionTimestamp": "2025-07-23T05:32:39Z",
    "sourceApi": "https://terraria.wiki.gg/api.php",
    "sourceFile": "terraPedia/data/raw/wiki/item-pages/yellowstainedglass.latest.json",
    "wikitextLength": 56
  },
  {
    "entityType": "item",
    "fetchedAt": "2026-03-28T03:14:03.347Z",
    "hasHtml": true,
    "hasRecipesMarkup": true,
    "hasWikitext": true,
    "htmlLength": 1673,
    "itemInternalName": "YellowString",
    "itemName": "Yellow String",
    "pageId": 8019,
    "pageTitle": "Yellow String",
    "recipesMarkupLength": 0,
    "requestedPageTitle": "Yellow String",
    "revisionTimestamp": "2025-07-24T10:48:01Z",
    "sourceApi": "https://terraria.wiki.gg/api.php",
    "sourceFile": "terraPedia/data/raw/wiki/item-pages/yellowstring.latest.json",
    "wikitextLength": 353
  },
  {
    "entityType": "item",
    "fetchedAt": "2026-03-28T01:43:18.356Z",
    "hasHtml": true,
    "hasRecipesMarkup": true,
    "hasWikitext": true,
    "htmlLength": 1078,
    "itemInternalName": "YellowStucco",
    "itemName": "Yellow Stucco",
    "pageId": 9030,
    "pageTitle": "Yellow Stucco",
    "recipesMarkupLength": 0,
    "requestedPageTitle": "Yellow Stucco",
    "revisionTimestamp": "2025-07-23T04:30:55Z",
    "sourceApi": "https://terraria.wiki.gg/api.php",
    "sourceFile": "terraPedia/data/raw/wiki/item-pages/yellowstucco.latest.json",
    "wikitextLength": 95
  },
  {
    "entityType": "item",
    "fetchedAt": "2026-03-28T01:43:24.339Z",
    "hasHtml": true,
    "hasRecipesMarkup": true,
    "hasWikitext": true,
    "htmlLength": 1097,
    "itemInternalName": "YellowStuccoWall",
    "itemName": "Yellow Stucco Wall",
    "pageId": 10178,
    "pageTitle": "Yellow Stucco Wall",
    "recipesMarkupLength": 0,
    "requestedPageTitle": "Yellow Stucco Wall",
    "revisionTimestamp": "2025-07-23T04:31:05Z",
    "sourceApi": "https://terraria.wiki.gg/api.php",
    "sourceFile": "terraPedia/data/raw/wiki/item-pages/yellowstuccowall.latest.json",
    "wikitextLength": 55
  },
  {
    "entityType": "item",
    "fetchedAt": "2026-03-28T01:37:05.285Z",
    "hasHtml": true,
    "hasRecipesMarkup": true,
    "hasWikitext": true,
    "htmlLength": 1118,
    "itemInternalName": "YellowTorch",
    "itemName": "Yellow Torch",
    "pageId": 5512,
    "pageTitle": "Yellow Torch",
    "recipesMarkupLength": 0,
    "requestedPageTitle": "Yellow Torch",
    "revisionTimestamp": "2025-07-24T10:48:10Z",
    "sourceApi": "https://terraria.wiki.gg/api.php",
    "sourceFile": "terraPedia/data/raw/wiki/item-pages/yellowtorch.latest.json",
    "wikitextLength": 150
  },
  {
    "entityType": "item",
    "fetchedAt": "2026-03-28T03:26:59.587Z",
    "hasHtml": true,
    "hasRecipesMarkup": true,
    "hasWikitext": true,
    "htmlLength": 1679,
    "itemInternalName": "YellowWrench",
    "itemName": "Yellow Wrench",
    "pageId": 10382,
    "pageTitle": "Yellow Wrench",
    "recipesMarkupLength": 0,
    "requestedPageTitle": "Yellow Wrench",
    "revisionTimestamp": "2025-07-23T06:56:13Z",
    "sourceApi": "https://terraria.wiki.gg/api.php",
    "sourceFile": "terraPedia/data/raw/wiki/item-pages/yellowwrench.latest.json",
    "wikitextLength": 107
  },
  {
    "entityType": "item",
    "fetchedAt": "2026-03-28T03:02:47.690Z",
    "hasHtml": true,
    "hasRecipesMarkup": true,
    "hasWikitext": true,
    "htmlLength": 1725,
    "itemInternalName": "YetiBanner",
    "itemName": "Yeti Banner",
    "pageId": 12338,
    "pageTitle": "Yeti Banner",
    "recipesMarkupLength": 0,
    "requestedPageTitle": "Yeti Banner",
    "revisionTimestamp": "2025-07-24T23:00:12Z",
    "sourceApi": "https://terraria.wiki.gg/api.php",
    "sourceFile": "terraPedia/data/raw/wiki/item-pages/yetibanner.latest.json",
    "wikitextLength": 374
  },
  {
    "entityType": "item",
    "fetchedAt": "2026-03-28T03:25:51.688Z",
    "hasHtml": true,
    "hasRecipesMarkup": true,
    "hasWikitext": true,
    "htmlLength": 1710,
    "itemInternalName": "Yoraiz0rDarkness",
    "itemName": "Yoraiz0r's Scowl",
    "pageId": 12272,
    "pageTitle": "Yoraiz0r's Scowl",
    "recipesMarkupLength": 0,
    "requestedPageTitle": "Yoraiz0r's Scowl",
    "revisionTimestamp": "2025-07-23T17:49:04Z",
    "sourceApi": "https://terraria.wiki.gg/api.php",
    "sourceFile": "terraPedia/data/raw/wiki/item-pages/yoraiz0rdarkness.latest.json",
    "wikitextLength": 442
  },
  {
    "entityType": "item",
    "fetchedAt": "2026-03-28T03:25:55.017Z",
    "hasHtml": true,
    "hasRecipesMarkup": true,
    "hasWikitext": true,
    "htmlLength": 1710,
    "itemInternalName": "Yoraiz0rHead",
    "itemName": "Yoraiz0r's Recolored Goggles",
    "pageId": 14401,
    "pageTitle": "Yoraiz0r's Recolored Goggles",
    "recipesMarkupLength": 0,
    "requestedPageTitle": "Yoraiz0r's Recolored Goggles",
    "revisionTimestamp": "2025-07-23T17:48:21Z",
    "sourceApi": "https://terraria.wiki.gg/api.php",
    "sourceFile": "terraPedia/data/raw/wiki/item-pages/yoraiz0rhead.latest.json",
    "wikitextLength": 382
  },
  {
    "entityType": "item",
    "fetchedAt": "2026-03-28T03:25:47.675Z",
    "hasHtml": true,
    "hasRecipesMarkup": true,
    "hasWikitext": true,
    "htmlLength": 1709,
    "itemInternalName": "Yoraiz0rPants",
    "itemName": "Yoraiz0r's Skirt",
    "pageId": 9990,
    "pageTitle": "Yoraiz0r's Skirt",
    "recipesMarkupLength": 0,
    "requestedPageTitle": "Yoraiz0r's Skirt",
    "revisionTimestamp": "2025-07-23T17:48:54Z",
    "sourceApi": "https://terraria.wiki.gg/api.php",
    "sourceFile": "terraPedia/data/raw/wiki/item-pages/yoraiz0rpants.latest.json",
    "wikitextLength": 382
  },
  {
    "entityType": "item",
    "fetchedAt": "2026-03-28T03:25:45.698Z",
    "hasHtml": true,
    "hasRecipesMarkup": true,
    "hasWikitext": true,
    "htmlLength": 1710,
    "itemInternalName": "Yoraiz0rShirt",
    "itemName": "Yoraiz0r's Uniform",
    "pageId": 10998,
    "pageTitle": "Yoraiz0r's Uniform",
    "recipesMarkupLength": 0,
    "requestedPageTitle": "Yoraiz0r's Uniform",
    "revisionTimestamp": "2025-07-23T17:48:34Z",
    "sourceApi": "https://terraria.wiki.gg/api.php",
    "sourceFile": "terraPedia/data/raw/wiki/item-pages/yoraiz0rshirt.latest.json",
    "wikitextLength": 382
  },
  {
    "entityType": "item",
    "fetchedAt": "2026-03-28T03:25:49.842Z",
    "hasHtml": true,
    "hasRecipesMarkup": true,
    "hasWikitext": true,
    "htmlLength": 206888,
    "itemInternalName": "Yoraiz0rWings",
    "itemName": "Yoraiz0r's Spell",
    "pageId": 6655,
    "pageTitle": "Yoraiz0r's Spell",
    "recipesMarkupLength": 0,
    "requestedPageTitle": "Yoraiz0r's Spell",
    "revisionTimestamp": "2026-02-18T20:45:24Z",
    "sourceApi": "https://terraria.wiki.gg/api.php",
    "sourceFile": "terraPedia/data/raw/wiki/item-pages/yoraiz0rwings.latest.json",
    "wikitextLength": 3310
  },
  {
    "entityType": "item",
    "fetchedAt": "2026-03-28T03:16:25.238Z",
    "hasHtml": true,
    "hasRecipesMarkup": true,
    "hasWikitext": true,
    "htmlLength": 179661,
    "itemInternalName": "YoyoBag",
    "itemName": "Yoyo Bag",
    "pageId": 6893,
    "pageTitle": "Yoyo Bag",
    "recipesMarkupLength": 1356,
    "requestedPageTitle": "Yoyo Bag",
    "revisionTimestamp": "2026-02-05T10:30:11Z",
    "sourceApi": "https://terraria.wiki.gg/api.php",
    "sourceFile": "terraPedia/data/raw/wiki/item-pages/yoyobag.latest.json",
    "wikitextLength": 2524
  },
  {
    "entityType": "item",
    "fetchedAt": "2026-03-28T03:15:14.707Z",
    "hasHtml": true,
    "hasRecipesMarkup": true,
    "hasWikitext": true,
    "htmlLength": 176222,
    "itemInternalName": "YoYoGlove",
    "itemName": "Yoyo Glove",
    "pageId": 13439,
    "pageTitle": "Yoyo Glove",
    "recipesMarkupLength": 0,
    "requestedPageTitle": "Yoyo Glove",
    "revisionTimestamp": "2026-03-23T15:36:21Z",
    "sourceApi": "https://terraria.wiki.gg/api.php",
    "sourceFile": "terraPedia/data/raw/wiki/item-pages/yoyoglove.latest.json",
    "wikitextLength": 1731
  },
  {
    "entityType": "item",
    "fetchedAt": "2026-03-28T04:27:16.169Z",
    "hasHtml": true,
    "hasRecipesMarkup": true,
    "hasWikitext": true,
    "htmlLength": 1726,
    "itemInternalName": "YuumaTheBlueTiger",
    "itemName": "Yuuma, The Blue Tiger",
    "pageId": 59544,
    "pageTitle": "Yuuma, The Blue Tiger",
    "recipesMarkupLength": 0,
    "requestedPageTitle": "Yuuma, The Blue Tiger",
    "revisionTimestamp": "2025-07-24T10:48:15Z",
    "sourceApi": "https://terraria.wiki.gg/api.php",
    "sourceFile": "terraPedia/data/raw/wiki/item-pages/yuumathebluetiger.latest.json",
    "wikitextLength": 133
  },
  {
    "entityType": "item",
    "fetchedAt": "2026-03-28T03:53:59.979Z",
    "hasHtml": true,
    "hasRecipesMarkup": true,
    "hasWikitext": true,
    "htmlLength": 123874,
    "itemInternalName": "ZapinatorGray",
    "itemName": "Gray Zapinator",
    "pageId": 15840,
    "pageTitle": "Gray Zapinator",
    "recipesMarkupLength": 0,
    "requestedPageTitle": "Gray Zapinator",
    "revisionTimestamp": "2026-03-04T22:27:09Z",
    "sourceApi": "https://terraria.wiki.gg/api.php",
    "sourceFile": "terraPedia/data/raw/wiki/item-pages/zapinatorgray.latest.json",
    "wikitextLength": 6410
  },
  {
    "entityType": "item",
    "fetchedAt": "2026-03-28T03:54:03.391Z",
    "hasHtml": true,
    "hasRecipesMarkup": true,
    "hasWikitext": true,
    "htmlLength": 124021,
    "itemInternalName": "ZapinatorOrange",
    "itemName": "Orange Zapinator",
    "pageId": 5149,
    "pageTitle": "Orange Zapinator",
    "recipesMarkupLength": 0,
    "requestedPageTitle": "Orange Zapinator",
    "revisionTimestamp": "2026-02-27T01:05:22Z",
    "sourceApi": "https://terraria.wiki.gg/api.php",
    "sourceFile": "terraPedia/data/raw/wiki/item-pages/zapinatororange.latest.json",
    "wikitextLength": 4509
  },
  {
    "entityType": "item",
    "fetchedAt": "2026-03-28T02:37:00.958Z",
    "hasHtml": true,
    "hasRecipesMarkup": true,
    "hasWikitext": true,
    "htmlLength": 1690,
    "itemInternalName": "ZebraSkin",
    "itemName": "Zebra Skin",
    "pageId": 4857,
    "pageTitle": "Zebra Skin",
    "recipesMarkupLength": 0,
    "requestedPageTitle": "Zebra Skin",
    "revisionTimestamp": "2025-07-23T04:23:08Z",
    "sourceApi": "https://terraria.wiki.gg/api.php",
    "sourceFile": "terraPedia/data/raw/wiki/item-pages/zebraskin.latest.json",
    "wikitextLength": 122
  },
  {
    "entityType": "item",
    "fetchedAt": "2026-03-28T02:28:28.148Z",
    "hasHtml": true,
    "hasRecipesMarkup": true,
    "hasWikitext": true,
    "htmlLength": 1150,
    "itemInternalName": "ZebraSwallowtailButterfly",
    "itemName": "Zebra Swallowtail Butterfly",
    "pageId": 11644,
    "pageTitle": "Zebra Swallowtail Butterfly",
    "recipesMarkupLength": 0,
    "requestedPageTitle": "Zebra Swallowtail Butterfly",
    "revisionTimestamp": "2025-07-23T18:31:27Z",
    "sourceApi": "https://terraria.wiki.gg/api.php",
    "sourceFile": "terraPedia/data/raw/wiki/item-pages/zebraswallowtailbutterfly.latest.json",
    "wikitextLength": 82
  },
  {
    "entityType": "item",
    "fetchedAt": "2026-03-28T02:33:38.621Z",
    "hasHtml": true,
    "hasRecipesMarkup": true,
    "hasWikitext": true,
    "htmlLength": 1102,
    "itemInternalName": "ZebraSwallowtailButterflyJar",
    "itemName": "Zebra Swallowtail Butterfly Jar",
    "pageId": 6428,
    "pageTitle": "Zebra Swallowtail Butterfly Jar",
    "recipesMarkupLength": 0,
    "requestedPageTitle": "Zebra Swallowtail Butterfly Jar",
    "revisionTimestamp": "2025-07-23T18:31:20Z",
    "sourceApi": "https://terraria.wiki.gg/api.php",
    "sourceFile": "terraPedia/data/raw/wiki/item-pages/zebraswallowtailbutterflyjar.latest.json",
    "wikitextLength": 78
  },
  {
    "entityType": "item",
    "fetchedAt": "2026-03-28T04:15:57.931Z",
    "hasHtml": true,
    "hasRecipesMarkup": true,
    "hasWikitext": true,
    "htmlLength": 264544,
    "itemInternalName": "Zenith",
    "itemName": "Zenith",
    "pageId": 4649,
    "pageTitle": "Zenith",
    "recipesMarkupLength": 2783,
    "requestedPageTitle": "Zenith",
    "revisionTimestamp": "2026-03-16T22:11:59Z",
    "sourceApi": "https://terraria.wiki.gg/api.php",
    "sourceFile": "terraPedia/data/raw/wiki/item-pages/zenith.latest.json",
    "wikitextLength": 10138
  },
  {
    "entityType": "item",
    "fetchedAt": "2026-03-28T02:42:18.463Z",
    "hasHtml": true,
    "hasRecipesMarkup": true,
    "hasWikitext": true,
    "htmlLength": 243154,
    "itemInternalName": "ZephyrFish",
    "itemName": "Zephyr Fish",
    "pageId": 10853,
    "pageTitle": "Zephyr Fish",
    "recipesMarkupLength": 0,
    "requestedPageTitle": "Zephyr Fish",
    "revisionTimestamp": "2025-02-05T20:34:34Z",
    "sourceApi": "https://terraria.wiki.gg/api.php",
    "sourceFile": "terraPedia/data/raw/wiki/item-pages/zephyrfish.latest.json",
    "wikitextLength": 1323
  },
  {
    "entityType": "item",
    "fetchedAt": "2026-03-28T02:07:09.714Z",
    "hasHtml": true,
    "hasRecipesMarkup": true,
    "hasWikitext": true,
    "htmlLength": 117052,
    "itemInternalName": "ZombieArm",
    "itemName": "Zombie Arm",
    "pageId": 11653,
    "pageTitle": "Zombie Arm",
    "recipesMarkupLength": 0,
    "requestedPageTitle": "Zombie Arm",
    "revisionTimestamp": "2026-03-01T13:06:57Z",
    "sourceApi": "https://terraria.wiki.gg/api.php",
    "sourceFile": "terraPedia/data/raw/wiki/item-pages/zombiearm.latest.json",
    "wikitextLength": 1936
  },
  {
    "entityType": "item",
    "fetchedAt": "2026-03-28T03:30:30.555Z",
    "hasHtml": true,
    "hasRecipesMarkup": true,
    "hasWikitext": true,
    "htmlLength": 1751,
    "itemInternalName": "ZombieArmStatue",
    "itemName": "Armed Zombie Statue",
    "pageId": 15948,
    "pageTitle": "Armed Zombie Statue",
    "recipesMarkupLength": 0,
    "requestedPageTitle": "Armed Zombie Statue",
    "revisionTimestamp": "2025-07-24T07:51:32Z",
    "sourceApi": "https://terraria.wiki.gg/api.php",
    "sourceFile": "terraPedia/data/raw/wiki/item-pages/zombiearmstatue.latest.json",
    "wikitextLength": 280
  },
  {
    "entityType": "item",
    "fetchedAt": "2026-03-28T02:18:51.595Z",
    "hasHtml": true,
    "hasRecipesMarkup": true,
    "hasWikitext": true,
    "htmlLength": 1404,
    "itemInternalName": "ZombieBanner",
    "itemName": "Zombie Banner",
    "pageId": 7684,
    "pageTitle": "Zombie Banner",
    "recipesMarkupLength": 0,
    "requestedPageTitle": "Zombie Banner",
    "revisionTimestamp": "2025-07-24T10:48:20Z",
    "sourceApi": "https://terraria.wiki.gg/api.php",
    "sourceFile": "terraPedia/data/raw/wiki/item-pages/zombiebanner.latest.json",
    "wikitextLength": 165
  },
  {
    "entityType": "item",
    "fetchedAt": "2026-03-28T03:02:49.738Z",
    "hasHtml": true,
    "hasRecipesMarkup": true,
    "hasWikitext": true,
    "htmlLength": 1736,
    "itemInternalName": "ZombieElfBanner",
    "itemName": "Zombie Elf Banner",
    "pageId": 7335,
    "pageTitle": "Zombie Elf Banner",
    "recipesMarkupLength": 0,
    "requestedPageTitle": "Zombie Elf Banner",
    "revisionTimestamp": "2025-07-24T23:00:16Z",
    "sourceApi": "https://terraria.wiki.gg/api.php",
    "sourceFile": "terraPedia/data/raw/wiki/item-pages/zombieelfbanner.latest.json",
    "wikitextLength": 380
  },
  {
    "entityType": "item",
    "fetchedAt": "2026-03-28T02:17:24.532Z",
    "hasHtml": true,
    "hasRecipesMarkup": true,
    "hasWikitext": true,
    "htmlLength": 1147,
    "itemInternalName": "ZombieEskimoBanner",
    "itemName": "Frozen Zombie Banner",
    "pageId": 5122,
    "pageTitle": "Frozen Zombie Banner",
    "recipesMarkupLength": 0,
    "requestedPageTitle": "Frozen Zombie Banner",
    "revisionTimestamp": "2025-07-24T08:46:14Z",
    "sourceApi": "https://terraria.wiki.gg/api.php",
    "sourceFile": "terraPedia/data/raw/wiki/item-pages/zombieeskimobanner.latest.json",
    "wikitextLength": 78
  },
  {
    "entityType": "item",
    "fetchedAt": "2026-03-28T02:43:58.341Z",
    "hasHtml": true,
    "hasRecipesMarkup": true,
    "hasWikitext": true,
    "htmlLength": 1394,
    "itemInternalName": "ZombieFish",
    "itemName": "Zombie Fish",
    "pageId": 4549,
    "pageTitle": "Zombie Fish",
    "recipesMarkupLength": 0,
    "requestedPageTitle": "Zombie Fish",
    "revisionTimestamp": "2025-07-24T23:00:21Z",
    "sourceApi": "https://terraria.wiki.gg/api.php",
    "sourceFile": "terraPedia/data/raw/wiki/item-pages/zombiefish.latest.json",
    "wikitextLength": 196
  },
  {
    "entityType": "item",
    "fetchedAt": "2026-03-28T04:00:06.625Z",
    "hasHtml": true,
    "hasRecipesMarkup": true,
    "hasWikitext": true,
    "htmlLength": 1742,
    "itemInternalName": "ZombieMermanBanner",
    "itemName": "Zombie Merman Banner",
    "pageId": 5551,
    "pageTitle": "Zombie Merman Banner",
    "recipesMarkupLength": 0,
    "requestedPageTitle": "Zombie Merman Banner",
    "revisionTimestamp": "2025-07-24T10:48:25Z",
    "sourceApi": "https://terraria.wiki.gg/api.php",
    "sourceFile": "terraPedia/data/raw/wiki/item-pages/zombiemermanbanner.latest.json",
    "wikitextLength": 164
  }
]
